{
  "img1.png": {
    "title": "비노",
    "description": "Be a Nomad, Be Free.\nAI / 시스템 구축 / 개발 / 디자인 / 공간 / 독서",
    "links": ["https://www.threads.com/@benobefree"],
    "tags": ["Profile"]
  },
  "img2.png": {
    "title": "마인드밍글",
    "description": "MBTI·애착이론을 중심으로 관계 패턴 분석, 연애 심리, 자기이해 콘텐츠를 제작하는 심리 콘텐츠 브랜드",
    "links": ["https://mindmingle.kr", "https://www.youtube.com/@mind_mingle"],
    "tags": ["Brand", "Website"]
  },
  "img3.png": {
    "title": "개러지 서클",
    "description": "경기북부 지역 기반의 성장 커뮤니티. 목표 달성과 깊이 있는 독서 나눔을 통해 함께 성장하는 프라이빗 커뮤니티",
    "links": ["https://thegaragecircle.com"],
    "tags": ["Community"]
  },
  "img4.png": {
    "title": "개발자의 디자인",
    "description": "개발자의 설계(design)로 완성된 제품, 개발자의 감각으로 만들어진 디자인(design)을 전시하는 공간",
    "links": ["https://devarte.xyz"],
    "tags": ["Website"]
  },
  "img5.png": {
    "title": "추천하는 책",
    "description": "◽ 내가 생각한 인생이 아니야 - 류시화\n◽ 함께 자라기 - 김창준\n◽ 시대예보: 호명사회 - 송길영\n◽ 열한 계단 - 채사장\n◽ 지적자본론 - 마스다 무네아키\n◽ 왜 그들만 부자가 되는가 - 필립 바구스\n◽ 레버리지 - 롭 무어",
    "links": [],
    "tags": ["Book"]
  }
}
